wsgipreload.py
wsgipreload-1.3.dist-info/METADATA
wsgipreload-1.3.dist-info/WHEEL
wsgipreload-1.3.dist-info/top_level.txt
wsgipreload-1.3.dist-info/RECORD
