Metadata-Version: 2.1
Name: wsgipreload
Version: 1.3
Summary: Preload WSGI applications by running a few URLs through the app immediately when it starts
Home-page: https://sourceforge.net/p/wsgipreload/
Author: Dave Brondsema
Author-email: dave@brondsema.net
License: Apache License
Platform: UNKNOWN
Requires: webob
